prcoords.py
prcoords-1.0.1.dist-info/METADATA
prcoords-1.0.1.dist-info/WHEEL
prcoords-1.0.1.dist-info/top_level.txt
prcoords-1.0.1.dist-info/RECORD
