Metadata-Version: 2.1
Name: prcoords
Version: 1.0.1
Summary: Public Domain library for rectifying Chinese coordinates (gcj-02/bd-09)
Home-page: https://github.com/Artoria2e5/PRCoords
Author: Mingye Wang
Author-email: arthur200126@gmail.com
License: UNKNOWN
Platform: UNKNOWN
Classifier: Programming Language :: Python :: 2
Classifier: Programming Language :: Python :: 3
Classifier: Development Status :: 5 - Production/Stable
Classifier: License :: CC0 1.0 Universal (CC0 1.0) Public Domain Dedication
Classifier: Operating System :: OS Independent
Classifier: Topic :: Scientific/Engineering :: GIS
